{"title":"1By-Day 16 06 15 Cherry Kiss XXX 1080p MP4","uid":14936254,"size":1939886481,"categoryP":"porn","categoryS":"hd___movies","magnet":"?xt=urn:btih:06855d6d68471d906e08ae90e7ee52d3a641beaa&amp;dn=1By-Day+16+06+15+Cherry+Kiss+XXX+1080p+MP4&amp;tr=udp%3A%2F%2Ftracker.leechers-paradise.org%3A6969&amp;tr=udp%3A%2F%2Fzer0day.ch%3A1337&amp;tr=udp%3A%2F%2Fopen.demonii.com%3A1337&amp;tr=udp%3A%2F%2Ftracker.coppersurfer.tk%3A6969&amp;tr=udp%3A%2F%2Fexodus.desync.com%3A6969","seeders":0,"leechers":0,"uploader":"RandalPaul","files":1,"time":1465999837,"description":"\n Media INFO &amp; Screenshots \n \n  Duration \t:  31min 35s \n  Size \t\t:  1.81 GiB \n  WidthxHeight \t:  1920x1080  \n  Video Format \t:  MPEG-4  \n\n  Image Links \t:  http://imgshag.com/image/gAa6d  \n\n  Image Sheet \t:  http://imgshag.com/image/gAc3Y \n\n \t \t \t Get More Small Sized XXX Videos \n \n \t   https://thepiratebay.se/user/RandalPaul/","torrent":{"xt":"urn:btih:06855d6d68471d906e08ae90e7ee52d3a641beaa","amp;dn":"1By-Day+16+06+15+Cherry+Kiss+XXX+1080p+MP4","amp;tr":["udp%3A%2F%2Ftracker.leechers-paradise.org%3A6969","udp%3A%2F%2Fzer0day.ch%3A1337","udp%3A%2F%2Fopen.demonii.com%3A1337","udp%3A%2F%2Ftracker.coppersurfer.tk%3A6969","udp%3A%2F%2Fexodus.desync.com%3A6969"],"infoHash":"06855d6d68471d906e08ae90e7ee52d3a641beaa","infoHashBuffer":{"type":"Buffer","data":[6,133,93,109,104,71,29,144,110,8,174,144,231,238,82,211,166,65,190,170]},"announce":[],"urlList":[]}}