{"title":"Assylum Audrey Holiday Assface XXX 1080p 16.06.09","uid":15046556,"size":1212225469,"categoryP":"porn","categoryS":"hd___movies","magnet":"?xt=urn:btih:0b198fbff1443b376747f40bd688bd93ad86e68e&amp;dn=Assylum+Audrey+Holiday+Assface+XXX+1080p+16.06.09&amp;tr=udp%3A%2F%2Ftracker.leechers-paradise.org%3A6969&amp;tr=udp%3A%2F%2Fzer0day.ch%3A1337&amp;tr=udp%3A%2F%2Fopen.demonii.com%3A1337&amp;tr=udp%3A%2F%2Ftracker.coppersurfer.tk%3A6969&amp;tr=udp%3A%2F%2Fexodus.desync.com%3A6969","seeders":0,"leechers":1,"uploader":"thfatboys","files":1,"time":1466640185,"description":"Screens: \nhttp://imgpeak.com/img-576adfeeaea87.html","torrent":{"xt":"urn:btih:0b198fbff1443b376747f40bd688bd93ad86e68e","amp;dn":"Assylum+Audrey+Holiday+Assface+XXX+1080p+16.06.09","amp;tr":["udp%3A%2F%2Ftracker.leechers-paradise.org%3A6969","udp%3A%2F%2Fzer0day.ch%3A1337","udp%3A%2F%2Fopen.demonii.com%3A1337","udp%3A%2F%2Ftracker.coppersurfer.tk%3A6969","udp%3A%2F%2Fexodus.desync.com%3A6969"],"infoHash":"0b198fbff1443b376747f40bd688bd93ad86e68e","infoHashBuffer":{"type":"Buffer","data":[11,25,143,191,241,68,59,55,103,71,244,11,214,136,189,147,173,134,230,142]},"announce":[],"urlList":[]}}