{"title":"femout xxx Adalyn Slate - Omar Presents Adalyn (Jun 14, 2016)","uid":14933133,"size":365077115,"categoryP":"porn","categoryS":"hd___movies","magnet":"?xt=urn:btih:0b6eecf48ef261a3bf01d63007c8e216b95ea602&amp;dn=femout+xxx+Adalyn+Slate+-+Omar+Presents+Adalyn+%28Jun+14%2C+2016%29&amp;tr=udp%3A%2F%2Ftracker.leechers-paradise.org%3A6969&amp;tr=udp%3A%2F%2Fzer0day.ch%3A1337&amp;tr=udp%3A%2F%2Fopen.demonii.com%3A1337&amp;tr=udp%3A%2F%2Ftracker.coppersurfer.tk%3A6969&amp;tr=udp%3A%2F%2Fexodus.desync.com%3A6969","seeders":0,"leechers":1,"uploader":"KayWily","files":1,"time":1465977102,"description":"femout xxx Adalyn Slate - Omar Presents Adalyn (Jun 14, 2016)\r\n\r\n \nhttp://porn-harbor.com/image/Nej","torrent":{"xt":"urn:btih:0b6eecf48ef261a3bf01d63007c8e216b95ea602","amp;dn":"femout+xxx+Adalyn+Slate+-+Omar+Presents+Adalyn+%28Jun+14%2C+2016%29","amp;tr":["udp%3A%2F%2Ftracker.leechers-paradise.org%3A6969","udp%3A%2F%2Fzer0day.ch%3A1337","udp%3A%2F%2Fopen.demonii.com%3A1337","udp%3A%2F%2Ftracker.coppersurfer.tk%3A6969","udp%3A%2F%2Fexodus.desync.com%3A6969"],"infoHash":"0b6eecf48ef261a3bf01d63007c8e216b95ea602","infoHashBuffer":{"type":"Buffer","data":[11,110,236,244,142,242,97,163,191,1,214,48,7,200,226,22,185,94,166,2]},"announce":[],"urlList":[]}}