{"title":"WWE.NXT.2016.01.06.720p.WEBRiP.h264-KYR","uid":13174146,"size":1938625204,"categoryP":"video","categoryS":"hd___tv_shows","magnet":"?xt=urn:btih:20b4326f5685b2a80e00d325ba7d6bc9d7806756&amp;dn=WWE.NXT.2016.01.06.720p.WEBRiP.h264-KYR&amp;tr=udp%3A%2F%2Ftracker.leechers-paradise.org%3A6969&amp;tr=udp%3A%2F%2Fzer0day.ch%3A1337&amp;tr=udp%3A%2F%2Fopen.demonii.com%3A1337&amp;tr=udp%3A%2F%2Ftracker.coppersurfer.tk%3A6969&amp;tr=udp%3A%2F%2Fexodus.desync.com%3A6969","seeders":0,"leechers":0,"uploader":null,"files":3,"time":1452271388,"description":"presents..\r\n\r\nk  n  o  w       y  o  u  r       r  o  l  e\r\n\r\n-- - -                                                      - - --\r\nWWE.NXT.2016.01.06.WEBRiP.h264-KYR\r\n-- - -                                                      - - --\r\ntitle [ WWE Superstars\r\ngenre [ Wrestling\r\nrel. date [ 01.06.16                   format [ h264\r\nair date [ 01.06.16                   source [ WEB\r\nruntime [ 58m 12s                   bitrate [ 4345kbps\r\nfilesize [ 1.81 GB                   resolu. [ 1280x720\r\nrar count [ 44x50mb                    frames [ 29.970\r\naudio [ 93.5kbps AAC\r\nlocation [ USA\r\n\r\n-\r\n\r\nUntouched stream rip not encoded.\r\n\r\nEnjoy!\r\n-\r\n\r\ngroup info\r\n\r\nKnow Your Role and Shut Your Mouth!\r\n\r\nwe are now looking for...\r\n\r\n(a) capper(s) of cable, PPV, good upspeed advantageous\r\n.. contact in the usual way.\r\n\r\nKYR respects...\r\n\r\neveryone keeping it real and oldschool. we love ya!\r\n\r\n--\r\nK N O W\r\nascii crafted by\r\nY O U R\r\nh8!HiGHONASCii\r\nR O L E","torrent":{"xt":"urn:btih:20b4326f5685b2a80e00d325ba7d6bc9d7806756","amp;dn":"WWE.NXT.2016.01.06.720p.WEBRiP.h264-KYR","amp;tr":["udp%3A%2F%2Ftracker.leechers-paradise.org%3A6969","udp%3A%2F%2Fzer0day.ch%3A1337","udp%3A%2F%2Fopen.demonii.com%3A1337","udp%3A%2F%2Ftracker.coppersurfer.tk%3A6969","udp%3A%2F%2Fexodus.desync.com%3A6969"],"infoHash":"20b4326f5685b2a80e00d325ba7d6bc9d7806756","infoHashBuffer":{"type":"Buffer","data":[32,180,50,111,86,133,178,168,14,0,211,37,186,125,107,201,215,128,103,86]},"announce":[],"urlList":[]}}