{"title":"The Best of Control XXX (NEW) DVDRip x264-Split Scenes","uid":15052166,"size":4384068813,"categoryP":"porn","categoryS":"other","magnet":"?xt=urn:btih:21abf4f64ad64e748853f5f5f0641105ebb53581&amp;dn=The+Best+of+Control+XXX+%28NEW%29+DVDRip+x264-Split+Scenes&amp;tr=udp%3A%2F%2Ftracker.leechers-paradise.org%3A6969&amp;tr=udp%3A%2F%2Fzer0day.ch%3A1337&amp;tr=udp%3A%2F%2Fopen.demonii.com%3A1337&amp;tr=udp%3A%2F%2Ftracker.coppersurfer.tk%3A6969&amp;tr=udp%3A%2F%2Fexodus.desync.com%3A6969","seeders":0,"leechers":1,"uploader":"LucasCar","files":10,"time":1466678008,"description":"Category: All Sex, Compilation, DP.\r\n\r\nCast: Jenna Haze, Sasha Grey, Teagan Presley, Audrey Bitoni, Alektra Blua, Rebeca Linares, Faye Reagan, Eva Angelina.\r\n\r\n.:Description:.\r\nTake a look at screenshots! Enjoy!\r\n \nhttp://imgteen.org/img-576b9ed214378.html\r\n \nhttp://imgteen.org/img-576b9ecc9e71a.html\r\n \nhttp://imgteen.org/img-576b9ec880b67.html\r\n \nhttp://imgteen.org/img-576b9ec204485.html\r\n \nhttp://imgteen.org/img-576b9ebe59528.html\r\n \nhttp://imgteen.org/img-576b9ebad9559.html\r\n \nhttp://imgteen.org/img-576b9eb426071.html\r\n \nhttp://imgteen.org/img-576b9eb067fc5.html\r\n \nhttp://imgteen.org/img-576b9eaa4f049.html\r\n\r\n\r\n\r\n★ ★ ★  For more Exclusive Porn please visit ★ ★ ★\r\n        \nhttps://thepiratebay.org/user/LucasCar","torrent":{"xt":"urn:btih:21abf4f64ad64e748853f5f5f0641105ebb53581","amp;dn":"The+Best+of+Control+XXX+%28NEW%29+DVDRip+x264-Split+Scenes","amp;tr":["udp%3A%2F%2Ftracker.leechers-paradise.org%3A6969","udp%3A%2F%2Fzer0day.ch%3A1337","udp%3A%2F%2Fopen.demonii.com%3A1337","udp%3A%2F%2Ftracker.coppersurfer.tk%3A6969","udp%3A%2F%2Fexodus.desync.com%3A6969"],"infoHash":"21abf4f64ad64e748853f5f5f0641105ebb53581","infoHashBuffer":{"type":"Buffer","data":[33,171,244,246,74,214,78,116,136,83,245,245,240,100,17,5,235,181,53,129]},"announce":[],"urlList":[]}}