{"title":"The.Goldbergs.S03E10.1080p.WEB-DL.DD5.1.H.264.mkv","uid":13417426,"size":894391500,"categoryP":"video","categoryS":"hd___tv_shows","magnet":"?xt=urn:btih:23c78531ba82c46cd73a567b24501f1ba9ade7e3&amp;dn=The.Goldbergs.S03E10.1080p.WEB-DL.DD5.1.H.264.mkv&amp;tr=udp%3A%2F%2Ftracker.leechers-paradise.org%3A6969&amp;tr=udp%3A%2F%2Fzer0day.ch%3A1337&amp;tr=udp%3A%2F%2Fopen.demonii.com%3A1337&amp;tr=udp%3A%2F%2Ftracker.coppersurfer.tk%3A6969&amp;tr=udp%3A%2F%2Fexodus.desync.com%3A6969","seeders":0,"leechers":1,"uploader":null,"files":1,"time":1454509431,"description":"The.Goldbergs.S03E10.1080p.WEB-DL.DD5.1.H.264.mkv","torrent":{"xt":"urn:btih:23c78531ba82c46cd73a567b24501f1ba9ade7e3","amp;dn":"The.Goldbergs.S03E10.1080p.WEB-DL.DD5.1.H.264.mkv","amp;tr":["udp%3A%2F%2Ftracker.leechers-paradise.org%3A6969","udp%3A%2F%2Fzer0day.ch%3A1337","udp%3A%2F%2Fopen.demonii.com%3A1337","udp%3A%2F%2Ftracker.coppersurfer.tk%3A6969","udp%3A%2F%2Fexodus.desync.com%3A6969"],"infoHash":"23c78531ba82c46cd73a567b24501f1ba9ade7e3","infoHashBuffer":{"type":"Buffer","data":[35,199,133,49,186,130,196,108,215,58,86,123,36,80,31,27,169,173,231,227]},"announce":[],"urlList":[]}}