{"title":"Zip file of strength training PDF books - new workouts!","uid":13256773,"size":2260282,"categoryP":"other","categoryS":"e_books","magnet":"?xt=urn:btih:253a6ebcf9f4c1a1e6646f3202534a07f7c52555&amp;dn=Zip+file+of+strength+training+PDF+books+-+new+workouts%21&amp;tr=udp%3A%2F%2Ftracker.leechers-paradise.org%3A6969&amp;tr=udp%3A%2F%2Fzer0day.ch%3A1337&amp;tr=udp%3A%2F%2Fopen.demonii.com%3A1337&amp;tr=udp%3A%2F%2Ftracker.coppersurfer.tk%3A6969&amp;tr=udp%3A%2F%2Fexodus.desync.com%3A6969","seeders":0,"leechers":1,"uploader":"cyriades","files":1,"time":1453224521,"description":"For more resources and writings -\r\n \nhttp://www.oddobjecttraining.com","torrent":{"xt":"urn:btih:253a6ebcf9f4c1a1e6646f3202534a07f7c52555","amp;dn":"Zip+file+of+strength+training+PDF+books+-+new+workouts%21","amp;tr":["udp%3A%2F%2Ftracker.leechers-paradise.org%3A6969","udp%3A%2F%2Fzer0day.ch%3A1337","udp%3A%2F%2Fopen.demonii.com%3A1337","udp%3A%2F%2Ftracker.coppersurfer.tk%3A6969","udp%3A%2F%2Fexodus.desync.com%3A6969"],"infoHash":"253a6ebcf9f4c1a1e6646f3202534a07f7c52555","infoHashBuffer":{"type":"Buffer","data":[37,58,110,188,249,244,193,161,230,100,111,50,2,83,74,7,247,197,37,85]},"announce":[],"urlList":[]}}