{"title":"[MyDirtyHobby] Sexy-Nikita - Notgeile Streife!","uid":13106969,"size":573757371,"categoryP":"porn","categoryS":"movie_clips","magnet":"?xt=urn:btih:26ed8b5b559afee7250c8d4da3364f1e4b804a9c&amp;dn=%5BMyDirtyHobby%5D+Sexy-Nikita+-+Notgeile+Streife%21&amp;tr=udp%3A%2F%2Ftracker.leechers-paradise.org%3A6969&amp;tr=udp%3A%2F%2Fzer0day.ch%3A1337&amp;tr=udp%3A%2F%2Fopen.demonii.com%3A1337&amp;tr=udp%3A%2F%2Ftracker.coppersurfer.tk%3A6969&amp;tr=udp%3A%2F%2Fexodus.desync.com%3A6969","seeders":0,"leechers":1,"uploader":"C47wh15p3r3r","files":1,"time":1451323869,"description":"[MyDirtyHobby] Sexy-Nikita - Notgeile Streife!\r\n\r\nScreenshots: \nhttp://imgarte.com/?v=355033 \nhttp://imgarte.com/?v=796157","torrent":{"xt":"urn:btih:26ed8b5b559afee7250c8d4da3364f1e4b804a9c","amp;dn":"%5BMyDirtyHobby%5D+Sexy-Nikita+-+Notgeile+Streife%21","amp;tr":["udp%3A%2F%2Ftracker.leechers-paradise.org%3A6969","udp%3A%2F%2Fzer0day.ch%3A1337","udp%3A%2F%2Fopen.demonii.com%3A1337","udp%3A%2F%2Ftracker.coppersurfer.tk%3A6969","udp%3A%2F%2Fexodus.desync.com%3A6969"],"infoHash":"26ed8b5b559afee7250c8d4da3364f1e4b804a9c","infoHashBuffer":{"type":"Buffer","data":[38,237,139,91,85,154,254,231,37,12,141,77,163,54,79,30,75,128,74,156]},"announce":[],"urlList":[]}}