{"title":"SIS CAT 2015 3D","uid":13418209,"size":69980377222,"categoryP":"applications","categoryS":"windows","magnet":"?xt=urn:btih:33b7f77f43e7fdfd0d423f3e361afe009900c401&amp;dn=SIS+CAT+2015+3D&amp;tr=udp%3A%2F%2Ftracker.leechers-paradise.org%3A6969&amp;tr=udp%3A%2F%2Fzer0day.ch%3A1337&amp;tr=udp%3A%2F%2Fopen.demonii.com%3A1337&amp;tr=udp%3A%2F%2Ftracker.coppersurfer.tk%3A6969&amp;tr=udp%3A%2F%2Fexodus.desync.com%3A6969","seeders":0,"leechers":1,"uploader":"eduardorocha2005","files":1,"time":1454519972,"description":"CATERPILLAR SIS 2015 DVD 2015 \r\n\r\nCaterpillar disc # 1: escavadeiras, OEM PRODUTOS \r\nCaterpillar Disco # 2: Geração de Energia Elétrica \r\nCaterpillar Disc # 3: motores marítimos, produtos petrolíferos, motores de caminhões \r\nCaterpillar Disc # 4: motores industriais \r\nCaterpillar Disc # 5 : escavadeiras, produtos OEM \r\nCaterpillar Disc # 6: assentadores de tubos, TRACK Tratores \r\nCaterpillar Disc # 7: INTEGRADA policultores, RODA DE TIPO carregadores, RASPADORES roda do trator \r\nCaterpillar Disc # 8: RODA DE TIPO LOADERS \r\nCaterpillar Disc # 9: Caminhões articulados, DESCARGA DE CARGA HAUL , PRODUTOS DE ORIENTAÇÃO controle da máquina, caminhões rodoviários de Desconto, CAMINHÕES Articulado Subterrâneo, na via rápida CAMINHÕES \r\nCaterpillar Disc # 10: retroescavadeiras, desafiadores, COMBINA, miniescavadeiras, minicarregadeiras, plantio direto, TELSCOPIC Manipuladores de Materiais, ferramentas de trabalho \r\nCaterpillar Disc # 11: ASFALTO pavers, Fresadoras, compactadores, motoniveladoras, Recuperadoras de Rodovias \r\nCaterpillar Disc # 12: escavadeiras \r\nCaterpillar Disc # 13: TRACK Tratores \r\nCaterpillar Disc # 14: escavadeiras, produtos OEM \r\nCaterpillar Disc # 15: escavadeiras, produtos OEM \r\nCaterpillar Disc # 16: EXCAVATORS , OEM PRODUTOS \r\nCaterpillar Disc # 17: Configuração de dados \r\nCaterpillar Disc # 18: Configuração de dados \r\nCaterpillar Disc # 19: Configuração de dados \r\nCaterpillar (Disc CD) # 20: Configuração \r\n\r\n\r\n\r\n\r\n Região: Todas as regiões    \r\n Idiomas: Inglês, espanhol, italiano, chinês, mexicano, Alemão, Francês    \r\n OS: VISTA, Win7 x32,     x64  Windows 8.0 8.1 8,2 x32  x64   WinNT, WinXP\r\n Quantidade de CD: 19 DVD DL e 1 CD    \r\n Data de atualização: 4/2015","torrent":{"xt":"urn:btih:33b7f77f43e7fdfd0d423f3e361afe009900c401","amp;dn":"SIS+CAT+2015+3D","amp;tr":["udp%3A%2F%2Ftracker.leechers-paradise.org%3A6969","udp%3A%2F%2Fzer0day.ch%3A1337","udp%3A%2F%2Fopen.demonii.com%3A1337","udp%3A%2F%2Ftracker.coppersurfer.tk%3A6969","udp%3A%2F%2Fexodus.desync.com%3A6969"],"infoHash":"33b7f77f43e7fdfd0d423f3e361afe009900c401","infoHashBuffer":{"type":"Buffer","data":[51,183,247,127,67,231,253,253,13,66,63,62,54,26,254,0,153,0,196,1]},"announce":[],"urlList":[]}}