{"title":"[MassageCreep] 2016-06-23 - Elsa Jean - Exploring Her Body [mp4]","uid":15053485,"size":1830650907,"categoryP":"porn","categoryS":"hd___movies","magnet":"?xt=urn:btih:40295f377efa60ff709ebc70747ca98bc91ea0a3&amp;dn=%5BMassageCreep%5D+2016-06-23+-+Elsa+Jean+-+Exploring+Her+Body+%5Bmp4%5D&amp;tr=udp%3A%2F%2Ftracker.leechers-paradise.org%3A6969&amp;tr=udp%3A%2F%2Fzer0day.ch%3A1337&amp;tr=udp%3A%2F%2Fopen.demonii.com%3A1337&amp;tr=udp%3A%2F%2Ftracker.coppersurfer.tk%3A6969&amp;tr=udp%3A%2F%2Fexodus.desync.com%3A6969","seeders":0,"leechers":1,"uploader":"Piratepr0n","files":1,"time":1466686214,"description":"-------------------------------------------------------------------------------------\nName:\n[MassageCreep] 2016-06-23 - Elsa Jean - Exploring Her Body [mp4][1920x1080]\n-------------------------------------------------------------------------------------\nFile list:\nmc.16.06.23.elsa.jean.exploring.her.body.int.mp4 (1.70 GiB | 1920x1080 | 41min 58s | MPEG-4) \nhttp://imgfapper.com/img-576bbefd7bd38.html","torrent":{"xt":"urn:btih:40295f377efa60ff709ebc70747ca98bc91ea0a3","amp;dn":"%5BMassageCreep%5D+2016-06-23+-+Elsa+Jean+-+Exploring+Her+Body+%5Bmp4%5D","amp;tr":["udp%3A%2F%2Ftracker.leechers-paradise.org%3A6969","udp%3A%2F%2Fzer0day.ch%3A1337","udp%3A%2F%2Fopen.demonii.com%3A1337","udp%3A%2F%2Ftracker.coppersurfer.tk%3A6969","udp%3A%2F%2Fexodus.desync.com%3A6969"],"infoHash":"40295f377efa60ff709ebc70747ca98bc91ea0a3","infoHashBuffer":{"type":"Buffer","data":[64,41,95,55,126,250,96,255,112,158,188,112,116,124,169,139,201,30,160,163]},"announce":[],"urlList":[]}}