{"title":"Kailashey Kelenkari - 720p - Upscaled - iamarnabpal","uid":14976804,"size":766730965,"categoryP":"video","categoryS":"movies","magnet":"?xt=urn:btih:4ca658143b5ed60ff5933465b2eff0f10144002c&amp;dn=Kailashey+Kelenkari+-+720p+-+Upscaled+-+iamarnabpal&amp;tr=udp%3A%2F%2Ftracker.leechers-paradise.org%3A6969&amp;tr=udp%3A%2F%2Fzer0day.ch%3A1337&amp;tr=udp%3A%2F%2Fopen.demonii.com%3A1337&amp;tr=udp%3A%2F%2Ftracker.coppersurfer.tk%3A6969&amp;tr=udp%3A%2F%2Fexodus.desync.com%3A6969","seeders":0,"leechers":0,"uploader":"apbangali","files":1,"time":1466243094,"description":"Much needed rip. only one available in the internet","torrent":{"xt":"urn:btih:4ca658143b5ed60ff5933465b2eff0f10144002c","amp;dn":"Kailashey+Kelenkari+-+720p+-+Upscaled+-+iamarnabpal","amp;tr":["udp%3A%2F%2Ftracker.leechers-paradise.org%3A6969","udp%3A%2F%2Fzer0day.ch%3A1337","udp%3A%2F%2Fopen.demonii.com%3A1337","udp%3A%2F%2Ftracker.coppersurfer.tk%3A6969","udp%3A%2F%2Fexodus.desync.com%3A6969"],"infoHash":"4ca658143b5ed60ff5933465b2eff0f10144002c","infoHashBuffer":{"type":"Buffer","data":[76,166,88,20,59,94,214,15,245,147,52,101,178,239,240,241,1,68,0,44]},"announce":[],"urlList":[]}}