{"title":"OfficePerils.Madalynn.Raye.And.Elizabeth.Andrews-Six.Inch.Heeled","uid":13139577,"size":465040409,"categoryP":"porn","categoryS":"movies","magnet":"?xt=urn:btih:4d34124e448117e873287d7f9a6fa53f22cd33f6&amp;dn=OfficePerils.Madalynn.Raye.And.Elizabeth.Andrews-Six.Inch.Heeled&amp;tr=udp%3A%2F%2Ftracker.leechers-paradise.org%3A6969&amp;tr=udp%3A%2F%2Fzer0day.ch%3A1337&amp;tr=udp%3A%2F%2Fopen.demonii.com%3A1337&amp;tr=udp%3A%2F%2Ftracker.coppersurfer.tk%3A6969&amp;tr=udp%3A%2F%2Fexodus.desync.com%3A6969","seeders":0,"leechers":1,"uploader":"jepsrmnt","files":1,"time":1451952447,"description":"OfficePerils.Madalynn.Raye.And.Elizabeth.Andrews-Six.Inch.Heeled.Posture.Training.XXX.720p.MP4.BTY\r\n\r\npreview \nhttp://booooty.com/?v=OfficePerils.Madalynn.Raye.And.Elizabeth.Andrews-Six.Inch.Heeled.Posture.Training.XXX.720p.MP4.BTY_s.jpg","torrent":{"xt":"urn:btih:4d34124e448117e873287d7f9a6fa53f22cd33f6","amp;dn":"OfficePerils.Madalynn.Raye.And.Elizabeth.Andrews-Six.Inch.Heeled","amp;tr":["udp%3A%2F%2Ftracker.leechers-paradise.org%3A6969","udp%3A%2F%2Fzer0day.ch%3A1337","udp%3A%2F%2Fopen.demonii.com%3A1337","udp%3A%2F%2Ftracker.coppersurfer.tk%3A6969","udp%3A%2F%2Fexodus.desync.com%3A6969"],"infoHash":"4d34124e448117e873287d7f9a6fa53f22cd33f6","infoHashBuffer":{"type":"Buffer","data":[77,52,18,78,68,129,23,232,115,40,125,127,154,111,165,63,34,205,51,246]},"announce":[],"urlList":[]}}