{"title":"TheArtPorn - Izi aka Iza, Ashley (Are you hot enough?) NEW 10 Ja","uid":13191279,"size":122026080,"categoryP":"porn","categoryS":"movie_clips","magnet":"?xt=urn:btih:517e571ffe5dcbeaa399a6a2a654aeb6f96ca6cf&amp;dn=TheArtPorn+-+Izi+aka+Iza%2C+Ashley+%28Are+you+hot+enough%3F%29+NEW+10+Ja&amp;tr=udp%3A%2F%2Ftracker.leechers-paradise.org%3A6969&amp;tr=udp%3A%2F%2Fzer0day.ch%3A1337&amp;tr=udp%3A%2F%2Fopen.demonii.com%3A1337&amp;tr=udp%3A%2F%2Ftracker.coppersurfer.tk%3A6969&amp;tr=udp%3A%2F%2Fexodus.desync.com%3A6969","seeders":0,"leechers":1,"uploader":"xxxlavalxxx","files":2,"time":1452437362,"description":"The sassy babe in this awesome glamour sex video is gonna totally blow your mind! Her boyfriend is not enough to satisfy her, so she initiates a wild threesome with two well-hung studs. She wants all of her tender holes to be filled with a meaty cock, and she could do this all night long. See this filthy cutie in action in this breathtaking artful porn movie that is full of absolutely unforgettable scenes.\r\nTags: Blowjob, Anal, Stockings, Brunette, Facial, Threesome\r\n \nhttp://imgdone.com/viewer.php?file=51658038889583383712.jpg\r\n \nhttp://imgdone.com/viewer.php?file=29643273809379249677.jpg","torrent":{"xt":"urn:btih:517e571ffe5dcbeaa399a6a2a654aeb6f96ca6cf","amp;dn":"TheArtPorn+-+Izi+aka+Iza%2C+Ashley+%28Are+you+hot+enough%3F%29+NEW+10+Ja","amp;tr":["udp%3A%2F%2Ftracker.leechers-paradise.org%3A6969","udp%3A%2F%2Fzer0day.ch%3A1337","udp%3A%2F%2Fopen.demonii.com%3A1337","udp%3A%2F%2Ftracker.coppersurfer.tk%3A6969","udp%3A%2F%2Fexodus.desync.com%3A6969"],"infoHash":"517e571ffe5dcbeaa399a6a2a654aeb6f96ca6cf","infoHashBuffer":{"type":"Buffer","data":[81,126,87,31,254,93,203,234,163,153,166,162,166,84,174,182,249,108,166,207]},"announce":[],"urlList":[]}}