{"title":"Jerk My Cock 2 XXX DVDRip x264-UPPERCUT","uid":13262052,"size":649207391,"categoryP":"porn","categoryS":"movies","magnet":"?xt=urn:btih:5a836c03cde83a0a21983cbc9d8ac7900176da96&amp;dn=Jerk+My+Cock+2+XXX+DVDRip+x264-UPPERCUT&amp;tr=udp%3A%2F%2Ftracker.leechers-paradise.org%3A6969&amp;tr=udp%3A%2F%2Fzer0day.ch%3A1337&amp;tr=udp%3A%2F%2Fopen.demonii.com%3A1337&amp;tr=udp%3A%2F%2Ftracker.coppersurfer.tk%3A6969&amp;tr=udp%3A%2F%2Fexodus.desync.com%3A6969","seeders":0,"leechers":0,"uploader":"0-DayXXX","files":1,"time":1453295617,"description":"------------------------------------------------\nJerk.My.Cock.2.XXX.DVDRip.x264-UPPERCUT\n------------------------------------------------\nScreenshot(s): \nhttp://imgsay.com/?v=220176 \n\n------------------------------------------------\nInfo(s):\nFormat:\t\tMPEG-4\nSize:\t\t619 MiB\nDuration:\t1h 33min\nResolution:\t720x404\nBitrate:\t805Kbps\n------------------------------------------------\n         ** More 0-DayXXX Uploads ** \nhttp://youpornbook.com\n------------------------------------------------\nIf you like this torrent, please post a comment!\n            Don't forget to seed!","torrent":{"xt":"urn:btih:5a836c03cde83a0a21983cbc9d8ac7900176da96","amp;dn":"Jerk+My+Cock+2+XXX+DVDRip+x264-UPPERCUT","amp;tr":["udp%3A%2F%2Ftracker.leechers-paradise.org%3A6969","udp%3A%2F%2Fzer0day.ch%3A1337","udp%3A%2F%2Fopen.demonii.com%3A1337","udp%3A%2F%2Ftracker.coppersurfer.tk%3A6969","udp%3A%2F%2Fexodus.desync.com%3A6969"],"infoHash":"5a836c03cde83a0a21983cbc9d8ac7900176da96","infoHashBuffer":{"type":"Buffer","data":[90,131,108,3,205,232,58,10,33,152,60,188,157,138,199,144,1,118,218,150]},"announce":[],"urlList":[]}}