{"title":"HandBrake-0.9.9-1_i686-lider","uid":13183895,"size":14543568,"categoryP":"applications","categoryS":"windows","magnet":"?xt=urn:btih:5df7df43a3387a92d3055a768337b7e591fa61ed&amp;dn=HandBrake-0.9.9-1_i686-lider&amp;tr=udp%3A%2F%2Ftracker.leechers-paradise.org%3A6969&amp;tr=udp%3A%2F%2Fzer0day.ch%3A1337&amp;tr=udp%3A%2F%2Fopen.demonii.com%3A1337&amp;tr=udp%3A%2F%2Ftracker.coppersurfer.tk%3A6969&amp;tr=udp%3A%2F%2Fexodus.desync.com%3A6969","seeders":0,"leechers":0,"uploader":"marceloz","files":5,"time":1452353540,"description":"Handbrake é um programa de código aberto gratuito com versões para Windows, Mac e Linux que comprime vídeos pesados sem perda de qualidade aparente. Para isso, ele utiliza codecs de vídeo e áudio avançados, como H.265 e AAC Passthru. O software também conta com predefinições para conversão para dispositivos móveis, como iPhone e iPod, e traz recursos para edição de DVDs, como inserção de legendas.\r\n\r\n\r\nHandBrake é compatível com\r\n\r\nSaída: AVI, MP4, MKV, OGM\r\nCodecs áudio: AAC, MP3, Vorbis e AC-3\r\nCodecs vídeo: MPEG-4, H.264 Theora\r\n\r\n\r\n\r\nbaixar blurays torrent- Especializado em Blu-Rays Compactados\r\n\r\nAO FIM DO DOWNLOAD FIQUE SEMEANDO/ENVIANDO, PARA QUE EU POSSA ENVIAR OUTROS FILMES COM QUALIDADE! Obrigado!\r\n\r\n\r\n----------------------SEMEAR SEMPRE","torrent":{"xt":"urn:btih:5df7df43a3387a92d3055a768337b7e591fa61ed","amp;dn":"HandBrake-0.9.9-1_i686-lider","amp;tr":["udp%3A%2F%2Ftracker.leechers-paradise.org%3A6969","udp%3A%2F%2Fzer0day.ch%3A1337","udp%3A%2F%2Fopen.demonii.com%3A1337","udp%3A%2F%2Ftracker.coppersurfer.tk%3A6969","udp%3A%2F%2Fexodus.desync.com%3A6969"],"infoHash":"5df7df43a3387a92d3055a768337b7e591fa61ed","infoHashBuffer":{"type":"Buffer","data":[93,247,223,67,163,56,122,146,211,5,90,118,131,55,183,229,145,250,97,237]},"announce":[],"urlList":[]}}