{"title":"Karate Approach to Calisthenics part 2 - PDF Book (updated)","uid":15086447,"size":104182,"categoryP":"other","categoryS":"e_books","magnet":"?xt=urn:btih:6b8d625bff7dc0a5488c42f622f05943851c0115&amp;dn=Karate+Approach+to+Calisthenics+part+2+-+PDF+Book+%28updated%29&amp;tr=udp%3A%2F%2Ftracker.leechers-paradise.org%3A6969&amp;tr=udp%3A%2F%2Fzer0day.ch%3A1337&amp;tr=udp%3A%2F%2Fopen.demonii.com%3A1337&amp;tr=udp%3A%2F%2Ftracker.coppersurfer.tk%3A6969&amp;tr=udp%3A%2F%2Fexodus.desync.com%3A6969","seeders":0,"leechers":0,"uploader":"cyriades","files":1,"time":1466887883,"description":"thanks","torrent":{"xt":"urn:btih:6b8d625bff7dc0a5488c42f622f05943851c0115","amp;dn":"Karate+Approach+to+Calisthenics+part+2+-+PDF+Book+%28updated%29","amp;tr":["udp%3A%2F%2Ftracker.leechers-paradise.org%3A6969","udp%3A%2F%2Fzer0day.ch%3A1337","udp%3A%2F%2Fopen.demonii.com%3A1337","udp%3A%2F%2Ftracker.coppersurfer.tk%3A6969","udp%3A%2F%2Fexodus.desync.com%3A6969"],"infoHash":"6b8d625bff7dc0a5488c42f622f05943851c0115","infoHashBuffer":{"type":"Buffer","data":[107,141,98,91,255,125,192,165,72,140,66,246,34,240,89,67,133,28,1,21]},"announce":[],"urlList":[]}}