{"title":"AssHoleFever - Arwen Gold - Anal Stretching Session - 21Sextury","uid":13096436,"size":705696590,"categoryP":"porn","categoryS":"hd___movies","magnet":"?xt=urn:btih:7badd89b2657785ba925e3981e9c423ce5638416&amp;dn=AssHoleFever+-+Arwen+Gold+-+Anal+Stretching+Session+-+21Sextury+&amp;tr=udp%3A%2F%2Ftracker.leechers-paradise.org%3A6969&amp;tr=udp%3A%2F%2Fzer0day.ch%3A1337&amp;tr=udp%3A%2F%2Fopen.demonii.com%3A1337&amp;tr=udp%3A%2F%2Ftracker.coppersurfer.tk%3A6969&amp;tr=udp%3A%2F%2Fexodus.desync.com%3A6969","seeders":0,"leechers":1,"uploader":"codho","files":1,"time":1451131038,"description":"AssHoleFever - Arwen Gold - Anal Stretching Session - 21Sextury ** NEW December 26, 2015 ** 720p\r\n\r\n\r\nScreens :\r\n \nhttp://imgaah.com/viewer.php?file=88204724021906226354.jpeg\r\n \nhttp://imgaah.com/viewer.php?file=15447063994055543572.jpg\r\n \nhttp://imgaah.com/viewer.php?file=92532348021086979399.jpg","torrent":{"xt":"urn:btih:7badd89b2657785ba925e3981e9c423ce5638416","amp;dn":"AssHoleFever+-+Arwen+Gold+-+Anal+Stretching+Session+-+21Sextury+","amp;tr":["udp%3A%2F%2Ftracker.leechers-paradise.org%3A6969","udp%3A%2F%2Fzer0day.ch%3A1337","udp%3A%2F%2Fopen.demonii.com%3A1337","udp%3A%2F%2Ftracker.coppersurfer.tk%3A6969","udp%3A%2F%2Fexodus.desync.com%3A6969"],"infoHash":"7badd89b2657785ba925e3981e9c423ce5638416","infoHashBuffer":{"type":"Buffer","data":[123,173,216,155,38,87,120,91,169,37,227,152,30,156,66,60,229,99,132,22]},"announce":[],"urlList":[]}}