{"title":"The.Scarehouse.2014.480p.x264-mSD","uid":15034955,"size":409608008,"categoryP":"video","categoryS":"movies","magnet":"?xt=urn:btih:8a45c8fccdf6e9c1e4cbf54d2d3955cd21b19c52&amp;dn=The.Scarehouse.2014.480p.x264-mSD&amp;tr=udp%3A%2F%2Ftracker.leechers-paradise.org%3A6969&amp;tr=udp%3A%2F%2Fzer0day.ch%3A1337&amp;tr=udp%3A%2F%2Fopen.demonii.com%3A1337&amp;tr=udp%3A%2F%2Ftracker.coppersurfer.tk%3A6969&amp;tr=udp%3A%2F%2Fexodus.desync.com%3A6969","seeders":0,"leechers":1,"uploader":"TvTeam","files":7,"time":1466570809,"description":"------------------------------------------------------------------------\r\n\r  https://www.torrenting.com\r\n\r\nSign up is OPEN - for time being. Come and have fun.\r\nHurry up sign up is open now!!!!","torrent":{"xt":"urn:btih:8a45c8fccdf6e9c1e4cbf54d2d3955cd21b19c52","amp;dn":"The.Scarehouse.2014.480p.x264-mSD","amp;tr":["udp%3A%2F%2Ftracker.leechers-paradise.org%3A6969","udp%3A%2F%2Fzer0day.ch%3A1337","udp%3A%2F%2Fopen.demonii.com%3A1337","udp%3A%2F%2Ftracker.coppersurfer.tk%3A6969","udp%3A%2F%2Fexodus.desync.com%3A6969"],"infoHash":"8a45c8fccdf6e9c1e4cbf54d2d3955cd21b19c52","infoHashBuffer":{"type":"Buffer","data":[138,69,200,252,205,246,233,193,228,203,245,77,45,57,85,205,33,177,156,82]},"announce":[],"urlList":[]}}