{"title":"BrutalInvasion E36 - Shrima Malati HD 1080p","uid":13428508,"size":1892005937,"categoryP":"porn","categoryS":"hd___movies","magnet":"?xt=urn:btih:8d46aa4a3c6a12bd4a7b0ec31c8afc54ad32a9fb&amp;dn=BrutalInvasion+E36+-+Shrima+Malati+HD+1080p&amp;tr=udp%3A%2F%2Ftracker.leechers-paradise.org%3A6969&amp;tr=udp%3A%2F%2Fzer0day.ch%3A1337&amp;tr=udp%3A%2F%2Fopen.demonii.com%3A1337&amp;tr=udp%3A%2F%2Ftracker.coppersurfer.tk%3A6969&amp;tr=udp%3A%2F%2Fexodus.desync.com%3A6969","seeders":0,"leechers":1,"uploader":"ElitePorn","files":1,"time":1454611231,"description":"BrutalInvasion E36 - Shrima Malati HD 1080p\r\n~~~~~~~~~~~~~~~~~~~~~~~~~~~~~~~~~~~~~~~~~~~\r\n\r\nScreenshots:\r\n~~~~~~~~~~~~ \nhttp://picturescream.com/x/clean/GeJa\r\n \nhttp://picturescream.com/x/clean/GeJm\r\n \nhttp://picturescream.com/x/clean/GeJk\r\n \nhttp://picturescream.com/x/clean/GeJE\r\n \nhttp://picturescream.com/x/clean/GeJK\r\n \nhttp://picturescream.com/x/clean/GeJS\r\n\r\n\r\nVideos Info:\r\n~~~~~~~~~~~~\r\nSize: 1.76 GB\r\nDuration: 30:40 min\t\r\nResolution: 1920x1080\r\n\r\n\r\nShow Your Appreciation - BitCoin: 1JxUQqRrvGC6txChvaZEbqSSsq9wtswoto","torrent":{"xt":"urn:btih:8d46aa4a3c6a12bd4a7b0ec31c8afc54ad32a9fb","amp;dn":"BrutalInvasion+E36+-+Shrima+Malati+HD+1080p","amp;tr":["udp%3A%2F%2Ftracker.leechers-paradise.org%3A6969","udp%3A%2F%2Fzer0day.ch%3A1337","udp%3A%2F%2Fopen.demonii.com%3A1337","udp%3A%2F%2Ftracker.coppersurfer.tk%3A6969","udp%3A%2F%2Fexodus.desync.com%3A6969"],"infoHash":"8d46aa4a3c6a12bd4a7b0ec31c8afc54ad32a9fb","infoHashBuffer":{"type":"Buffer","data":[141,70,170,74,60,106,18,189,74,123,14,195,28,138,252,84,173,50,169,251]},"announce":[],"urlList":[]}}