{"title":"PornPros - Hot girl Molly Jane sensually fuck","uid":13258082,"size":111205724,"categoryP":"porn","categoryS":"movie_clips","magnet":"?xt=urn:btih:9af035dd64ad7c04dea0c8b787ccd6e3ad3a2484&amp;dn=PornPros+-+Hot+girl+Molly+Jane+sensually+fuck&amp;tr=udp%3A%2F%2Ftracker.leechers-paradise.org%3A6969&amp;tr=udp%3A%2F%2Fzer0day.ch%3A1337&amp;tr=udp%3A%2F%2Fopen.demonii.com%3A1337&amp;tr=udp%3A%2F%2Ftracker.coppersurfer.tk%3A6969&amp;tr=udp%3A%2F%2Fexodus.desync.com%3A6969","seeders":0,"leechers":1,"uploader":"demonoidt","files":1,"time":1453236075,"description":"Samples\r\n \nhttp://adultwallpapers.co.in/pornpros-hot-girl-molly-jane-sensually-fuck/\r\n \nhttp://adultwallpapers.co.in/pornpros-hot-girl-molly-jane-sensually-fuck-2/\r\n \nhttp://adultwallpapers.co.in/pornpros-hot-girl-molly-jane-sensually-fuck-3/\r\n \nhttp://demonoid.co/2016/01/19/pornpros-hot-girl-molly-jane-sensually-fuck/","torrent":{"xt":"urn:btih:9af035dd64ad7c04dea0c8b787ccd6e3ad3a2484","amp;dn":"PornPros+-+Hot+girl+Molly+Jane+sensually+fuck","amp;tr":["udp%3A%2F%2Ftracker.leechers-paradise.org%3A6969","udp%3A%2F%2Fzer0day.ch%3A1337","udp%3A%2F%2Fopen.demonii.com%3A1337","udp%3A%2F%2Ftracker.coppersurfer.tk%3A6969","udp%3A%2F%2Fexodus.desync.com%3A6969"],"infoHash":"9af035dd64ad7c04dea0c8b787ccd6e3ad3a2484","infoHashBuffer":{"type":"Buffer","data":[154,240,53,221,100,173,124,4,222,160,200,183,135,204,214,227,173,58,36,132]},"announce":[],"urlList":[]}}