{"title":"[ThisGirlSucks] 2015-12-23 - Callie Cyprus - Tattooed Hottie Str","uid":13082051,"size":1170236053,"categoryP":"porn","categoryS":"hd___movies","magnet":"?xt=urn:btih:b133845e1d88647f37569c91d4fcc878ba2f4ce0&amp;dn=%5BThisGirlSucks%5D+2015-12-23+-+Callie+Cyprus+-+Tattooed+Hottie+Str&amp;tr=udp%3A%2F%2Ftracker.leechers-paradise.org%3A6969&amp;tr=udp%3A%2F%2Fzer0day.ch%3A1337&amp;tr=udp%3A%2F%2Fopen.demonii.com%3A1337&amp;tr=udp%3A%2F%2Ftracker.coppersurfer.tk%3A6969&amp;tr=udp%3A%2F%2Fexodus.desync.com%3A6969","seeders":0,"leechers":1,"uploader":"Piratepr0n","files":1,"time":1450909572,"description":"-------------------------------------------------------------------------------------\nName:\n[ThisGirlSucks] 2015-12-23 - Callie Cyprus - Tattooed Hottie Strokes And Sucks [mp4][1920x1080]\n-------------------------------------------------------------------------------------\nFile list:\ntgs.15.12.23.callie.cyprus.mp4 (1.09 GiB | 1920x1080 | 12min 48s | MPEG-4) \nhttp://imgfapper.com/img-567b116d14adc.html","torrent":{"xt":"urn:btih:b133845e1d88647f37569c91d4fcc878ba2f4ce0","amp;dn":"%5BThisGirlSucks%5D+2015-12-23+-+Callie+Cyprus+-+Tattooed+Hottie+Str","amp;tr":["udp%3A%2F%2Ftracker.leechers-paradise.org%3A6969","udp%3A%2F%2Fzer0day.ch%3A1337","udp%3A%2F%2Fopen.demonii.com%3A1337","udp%3A%2F%2Ftracker.coppersurfer.tk%3A6969","udp%3A%2F%2Fexodus.desync.com%3A6969"],"infoHash":"b133845e1d88647f37569c91d4fcc878ba2f4ce0","infoHashBuffer":{"type":"Buffer","data":[177,51,132,94,29,136,100,127,55,86,156,145,212,252,200,120,186,47,76,224]},"announce":[],"urlList":[]}}