{"title":"FirstAnalQuest Rebecca Rainbow XXX 16.06.22","uid":15046570,"size":258012907,"categoryP":"porn","categoryS":"movie_clips","magnet":"?xt=urn:btih:b571bad87d604f15840a7ac39c1f40bed8e07d8e&amp;dn=FirstAnalQuest+Rebecca+Rainbow+XXX+16.06.22&amp;tr=udp%3A%2F%2Ftracker.leechers-paradise.org%3A6969&amp;tr=udp%3A%2F%2Fzer0day.ch%3A1337&amp;tr=udp%3A%2F%2Fopen.demonii.com%3A1337&amp;tr=udp%3A%2F%2Ftracker.coppersurfer.tk%3A6969&amp;tr=udp%3A%2F%2Fexodus.desync.com%3A6969","seeders":0,"leechers":1,"uploader":"thfatboys","files":1,"time":1466640247,"description":"Screens: \nhttp://imgpeak.com/img-576ae003a3112.html","torrent":{"xt":"urn:btih:b571bad87d604f15840a7ac39c1f40bed8e07d8e","amp;dn":"FirstAnalQuest+Rebecca+Rainbow+XXX+16.06.22","amp;tr":["udp%3A%2F%2Ftracker.leechers-paradise.org%3A6969","udp%3A%2F%2Fzer0day.ch%3A1337","udp%3A%2F%2Fopen.demonii.com%3A1337","udp%3A%2F%2Ftracker.coppersurfer.tk%3A6969","udp%3A%2F%2Fexodus.desync.com%3A6969"],"infoHash":"b571bad87d604f15840a7ac39c1f40bed8e07d8e","infoHashBuffer":{"type":"Buffer","data":[181,113,186,216,125,96,79,21,132,10,122,195,156,31,64,190,216,224,125,142]},"announce":[],"urlList":[]}}