{"title":"[TeensLikeItBig / Brazzers] Kylie Nicole (Teen Trophy Wife / 27.","uid":14705884,"size":234057870,"categoryP":"porn","categoryS":"movie_clips","magnet":"?xt=urn:btih:c1382ea6400469a17f0dcceb8ef6a50c33b95fa6&amp;dn=%5BTeensLikeItBig+%2F+Brazzers%5D+Kylie+Nicole+%28Teen+Trophy+Wife+%2F+27.&amp;tr=udp%3A%2F%2Ftracker.leechers-paradise.org%3A6969&amp;tr=udp%3A%2F%2Fzer0day.ch%3A1337&amp;tr=udp%3A%2F%2Fopen.demonii.com%3A1337&amp;tr=udp%3A%2F%2Ftracker.coppersurfer.tk%3A6969&amp;tr=udp%3A%2F%2Fexodus.desync.com%3A6969","seeders":0,"leechers":1,"uploader":"LucasCar","files":1,"time":1464357735,"description":"[TeensLikeItBig / Brazzers] Kylie Nicole (Teen Trophy Wife / 27.05.16)\r\n \nhttp://voyeurimage.org/img-574836c93d309.html\r\n \nhttp://voyeurimage.org/img-574836eef2267.html\r\n\r\n\r\n\r\n\r\n★ ★ ★  For more Exclusive Porn please visit ★ ★ ★\r\n   \nhttps://thepiratebay.org/user/LucasCar","torrent":{"xt":"urn:btih:c1382ea6400469a17f0dcceb8ef6a50c33b95fa6","amp;dn":"%5BTeensLikeItBig+%2F+Brazzers%5D+Kylie+Nicole+%28Teen+Trophy+Wife+%2F+27.","amp;tr":["udp%3A%2F%2Ftracker.leechers-paradise.org%3A6969","udp%3A%2F%2Fzer0day.ch%3A1337","udp%3A%2F%2Fopen.demonii.com%3A1337","udp%3A%2F%2Ftracker.coppersurfer.tk%3A6969","udp%3A%2F%2Fexodus.desync.com%3A6969"],"infoHash":"c1382ea6400469a17f0dcceb8ef6a50c33b95fa6","infoHashBuffer":{"type":"Buffer","data":[193,56,46,166,64,4,105,161,127,13,204,235,142,246,165,12,51,185,95,166]},"announce":[],"urlList":[]}}