{"title":"My Friend's Hot Girl - Kimber Woods { 06.15.2016 } NEW 2016","uid":14933843,"size":223656023,"categoryP":"porn","categoryS":"movie_clips","magnet":"?xt=urn:btih:c54ba245b86bce1ad19e98638333f8b12276ab3b&amp;dn=My+Friend%27s+Hot+Girl+-+Kimber+Woods+%7B+06.15.2016+%7D+NEW+2016&amp;tr=udp%3A%2F%2Ftracker.leechers-paradise.org%3A6969&amp;tr=udp%3A%2F%2Fzer0day.ch%3A1337&amp;tr=udp%3A%2F%2Fopen.demonii.com%3A1337&amp;tr=udp%3A%2F%2Ftracker.coppersurfer.tk%3A6969&amp;tr=udp%3A%2F%2Fexodus.desync.com%3A6969","seeders":0,"leechers":1,"uploader":"Superporn","files":1,"time":1465981524,"description":"Johnny and his friend get home late after a night of partying. His friend is completely passed out and his friend's wife, Kimber Woods, is upset because she was expecting cock. Since her man can't give her what she wanted she turns to Johnny to fulfill her needs","torrent":{"xt":"urn:btih:c54ba245b86bce1ad19e98638333f8b12276ab3b","amp;dn":"My+Friend%27s+Hot+Girl+-+Kimber+Woods+%7B+06.15.2016+%7D+NEW+2016","amp;tr":["udp%3A%2F%2Ftracker.leechers-paradise.org%3A6969","udp%3A%2F%2Fzer0day.ch%3A1337","udp%3A%2F%2Fopen.demonii.com%3A1337","udp%3A%2F%2Ftracker.coppersurfer.tk%3A6969","udp%3A%2F%2Fexodus.desync.com%3A6969"],"infoHash":"c54ba245b86bce1ad19e98638333f8b12276ab3b","infoHashBuffer":{"type":"Buffer","data":[197,75,162,69,184,107,206,26,209,158,152,99,131,51,248,177,34,118,171,59]},"announce":[],"urlList":[]}}