{"title":"Dire Starits dts 5.1","uid":15053560,"size":424391227,"categoryP":"audio","categoryS":"music","magnet":"?xt=urn:btih:d746db3afe398df2a327c847a248230453b83478&amp;dn=Dire+Starits+dts+5.1&amp;tr=udp%3A%2F%2Ftracker.leechers-paradise.org%3A6969&amp;tr=udp%3A%2F%2Fzer0day.ch%3A1337&amp;tr=udp%3A%2F%2Fopen.demonii.com%3A1337&amp;tr=udp%3A%2F%2Ftracker.coppersurfer.tk%3A6969&amp;tr=udp%3A%2F%2Fexodus.desync.com%3A6969","seeders":0,"leechers":1,"uploader":"brexit","files":8,"time":1466687085,"description":"Dire Starits - Calling Elvis.dts\r\nDire Starits - Heavy fuel.dts\r\nDire Starits - Money for nothing.dts\r\nDire Starits - So far away.dts\r\nDire Starits - Sultans of Swing.dts\r\nDire Starits - Twisting by the Pool.dts\r\nDire Starits - Walk of life.dts\r\nDire Starits - Why Worry.dts","torrent":{"xt":"urn:btih:d746db3afe398df2a327c847a248230453b83478","amp;dn":"Dire+Starits+dts+5.1","amp;tr":["udp%3A%2F%2Ftracker.leechers-paradise.org%3A6969","udp%3A%2F%2Fzer0day.ch%3A1337","udp%3A%2F%2Fopen.demonii.com%3A1337","udp%3A%2F%2Ftracker.coppersurfer.tk%3A6969","udp%3A%2F%2Fexodus.desync.com%3A6969"],"infoHash":"d746db3afe398df2a327c847a248230453b83478","infoHashBuffer":{"type":"Buffer","data":[215,70,219,58,254,57,141,242,163,39,200,71,162,72,35,4,83,184,52,120]},"announce":[],"urlList":[]}}