{"title":"Mock.the.Week.S15E02.480p.x264-mSD","uid":15119977,"size":152395228,"categoryP":"video","categoryS":"tv_shows","magnet":"?xt=urn:btih:d757975f28b0381a627482f931585f4ddcc671df&amp;dn=Mock.the.Week.S15E02.480p.x264-mSD&amp;tr=udp%3A%2F%2Ftracker.leechers-paradise.org%3A6969&amp;tr=udp%3A%2F%2Fzer0day.ch%3A1337&amp;tr=udp%3A%2F%2Fopen.demonii.com%3A1337&amp;tr=udp%3A%2F%2Ftracker.coppersurfer.tk%3A6969&amp;tr=udp%3A%2F%2Fexodus.desync.com%3A6969","seeders":0,"leechers":1,"uploader":"TvTeam","files":7,"time":1467068370,"description":"https://www.torrenting.com\r\n\r\nSign up is OPEN - for time being. Come and have fun","torrent":{"xt":"urn:btih:d757975f28b0381a627482f931585f4ddcc671df","amp;dn":"Mock.the.Week.S15E02.480p.x264-mSD","amp;tr":["udp%3A%2F%2Ftracker.leechers-paradise.org%3A6969","udp%3A%2F%2Fzer0day.ch%3A1337","udp%3A%2F%2Fopen.demonii.com%3A1337","udp%3A%2F%2Ftracker.coppersurfer.tk%3A6969","udp%3A%2F%2Fexodus.desync.com%3A6969"],"infoHash":"d757975f28b0381a627482f931585f4ddcc671df","infoHashBuffer":{"type":"Buffer","data":[215,87,151,95,40,176,56,26,98,116,130,249,49,88,95,77,220,198,113,223]},"announce":[],"urlList":[]}}