{"title":"China Black with the Ass","uid":13078483,"size":134637499,"categoryP":"porn","categoryS":"movie_clips","magnet":"?xt=urn:btih:d8e02448f8f6c1a435d9524213859d7c929e4cc4&amp;dn=China+Black+with+the+Ass&amp;tr=udp%3A%2F%2Ftracker.leechers-paradise.org%3A6969&amp;tr=udp%3A%2F%2Fzer0day.ch%3A1337&amp;tr=udp%3A%2F%2Fopen.demonii.com%3A1337&amp;tr=udp%3A%2F%2Ftracker.coppersurfer.tk%3A6969&amp;tr=udp%3A%2F%2Fexodus.desync.com%3A6969","seeders":0,"leechers":0,"uploader":"Piratepr0n","files":1,"time":1450878658,"description":"-------------------------------------------------------------------------------------\nName:\nChina Black with the Ass\n-------------------------------------------------------------------------------------\nFile list:\nChina Black with the Ass.flv (128 MiB | 544x408 | 35min 20s | Flash Video) \nhttp://imgfapper.com/img-567a98ae893d8.html","torrent":{"xt":"urn:btih:d8e02448f8f6c1a435d9524213859d7c929e4cc4","amp;dn":"China+Black+with+the+Ass","amp;tr":["udp%3A%2F%2Ftracker.leechers-paradise.org%3A6969","udp%3A%2F%2Fzer0day.ch%3A1337","udp%3A%2F%2Fopen.demonii.com%3A1337","udp%3A%2F%2Ftracker.coppersurfer.tk%3A6969","udp%3A%2F%2Fexodus.desync.com%3A6969"],"infoHash":"d8e02448f8f6c1a435d9524213859d7c929e4cc4","infoHashBuffer":{"type":"Buffer","data":[216,224,36,72,248,246,193,164,53,217,82,66,19,133,157,124,146,158,76,196]},"announce":[],"urlList":[]}}