{"title":"Annette Schwarz Anal","uid":13379278,"size":179328839,"categoryP":"porn","categoryS":"movie_clips","magnet":"?xt=urn:btih:dfc13b499e41fbaf7ac3e2ec12e3fc4bea984220&amp;dn=Annette+Schwarz+Anal&amp;tr=udp%3A%2F%2Ftracker.leechers-paradise.org%3A6969&amp;tr=udp%3A%2F%2Fzer0day.ch%3A1337&amp;tr=udp%3A%2F%2Fopen.demonii.com%3A1337&amp;tr=udp%3A%2F%2Ftracker.coppersurfer.tk%3A6969&amp;tr=udp%3A%2F%2Fexodus.desync.com%3A6969","seeders":0,"leechers":0,"uploader":"Piratepr0n","files":1,"time":1454256103,"description":"-------------------------------------------------------------------------------------\nName:\nAnnette Schwarz Anal\n-------------------------------------------------------------------------------------\nFile list:\nAnnette Schwarz Anal.flv (171 MiB | 550x404 | 47min 12s | Flash Video) \nhttp://imgfapper.com/img-56ae21cc577d8.html","torrent":{"xt":"urn:btih:dfc13b499e41fbaf7ac3e2ec12e3fc4bea984220","amp;dn":"Annette+Schwarz+Anal","amp;tr":["udp%3A%2F%2Ftracker.leechers-paradise.org%3A6969","udp%3A%2F%2Fzer0day.ch%3A1337","udp%3A%2F%2Fopen.demonii.com%3A1337","udp%3A%2F%2Ftracker.coppersurfer.tk%3A6969","udp%3A%2F%2Fexodus.desync.com%3A6969"],"infoHash":"dfc13b499e41fbaf7ac3e2ec12e3fc4bea984220","infoHashBuffer":{"type":"Buffer","data":[223,193,59,73,158,65,251,175,122,195,226,236,18,227,252,75,234,152,66,32]},"announce":[],"urlList":[]}}