{"title":"BangBus.16.06.22.Alyssa.Cole.XXX.1080p","uid":15038367,"size":4102011753,"categoryP":"porn","categoryS":"movie_clips","magnet":"?xt=urn:btih:e228a3eada2e27f3c0bc7a9ee99d738ebf478183&amp;dn=BangBus.16.06.22.Alyssa.Cole.XXX.1080p&amp;tr=udp%3A%2F%2Ftracker.leechers-paradise.org%3A6969&amp;tr=udp%3A%2F%2Fzer0day.ch%3A1337&amp;tr=udp%3A%2F%2Fopen.demonii.com%3A1337&amp;tr=udp%3A%2F%2Ftracker.coppersurfer.tk%3A6969&amp;tr=udp%3A%2F%2Fexodus.desync.com%3A6969","seeders":0,"leechers":1,"uploader":"distinc","files":1,"time":1466601695,"description":"BangBus.16.06.22.Alyssa.Cole.XXX.1080p\r\n\r\nScreenShoTs:\r\n \nhttp://imagedisco.net/?v=3474066984\r\n \nhttp://imagedisco.net/?g=688397652","torrent":{"xt":"urn:btih:e228a3eada2e27f3c0bc7a9ee99d738ebf478183","amp;dn":"BangBus.16.06.22.Alyssa.Cole.XXX.1080p","amp;tr":["udp%3A%2F%2Ftracker.leechers-paradise.org%3A6969","udp%3A%2F%2Fzer0day.ch%3A1337","udp%3A%2F%2Fopen.demonii.com%3A1337","udp%3A%2F%2Ftracker.coppersurfer.tk%3A6969","udp%3A%2F%2Fexodus.desync.com%3A6969"],"infoHash":"e228a3eada2e27f3c0bc7a9ee99d738ebf478183","infoHashBuffer":{"type":"Buffer","data":[226,40,163,234,218,46,39,243,192,188,122,158,233,157,115,142,191,71,129,131]},"announce":[],"urlList":[]}}