{"title":"Indian Nice Teen Fucking Hard","uid":13210106,"size":78913744,"categoryP":"porn","categoryS":"movie_clips","magnet":"?xt=urn:btih:f0a68752fb2290c9c7afd421189ff1cec290ec18&amp;dn=Indian+Nice+Teen+Fucking+Hard&amp;tr=udp%3A%2F%2Ftracker.leechers-paradise.org%3A6969&amp;tr=udp%3A%2F%2Fzer0day.ch%3A1337&amp;tr=udp%3A%2F%2Fopen.demonii.com%3A1337&amp;tr=udp%3A%2F%2Ftracker.coppersurfer.tk%3A6969&amp;tr=udp%3A%2F%2Fexodus.desync.com%3A6969","seeders":0,"leechers":1,"uploader":"demonoidt","files":1,"time":1452635527,"description":"Samples\r\n \nhttp://adultwallpapers.co.in/indian-nice-teen-fucking-hard/\r\n \nhttp://adultwallpapers.co.in/indian-nice-teen-fucking-hard-2/\r\n \nhttp://adultwallpapers.co.in/indian-nice-teen-fucking-hard-3/\r\n \nhttp://demonoid.co/2016/01/12/indian-nice-teen-fucking-hard/","torrent":{"xt":"urn:btih:f0a68752fb2290c9c7afd421189ff1cec290ec18","amp;dn":"Indian+Nice+Teen+Fucking+Hard","amp;tr":["udp%3A%2F%2Ftracker.leechers-paradise.org%3A6969","udp%3A%2F%2Fzer0day.ch%3A1337","udp%3A%2F%2Fopen.demonii.com%3A1337","udp%3A%2F%2Ftracker.coppersurfer.tk%3A6969","udp%3A%2F%2Fexodus.desync.com%3A6969"],"infoHash":"f0a68752fb2290c9c7afd421189ff1cec290ec18","infoHashBuffer":{"type":"Buffer","data":[240,166,135,82,251,34,144,201,199,175,212,33,24,159,241,206,194,144,236,24]},"announce":[],"urlList":[]}}