{"title":"Degrassi.Next.Class.S01E01.XviD-AFG","uid":13142070,"size":335590319,"categoryP":"video","categoryS":"tv_shows","magnet":"?xt=urn:btih:f9197ce35a7830c5e981a5f373c9dc972b980972&amp;dn=Degrassi.Next.Class.S01E01.XviD-AFG&amp;tr=udp%3A%2F%2Ftracker.leechers-paradise.org%3A6969&amp;tr=udp%3A%2F%2Fzer0day.ch%3A1337&amp;tr=udp%3A%2F%2Fopen.demonii.com%3A1337&amp;tr=udp%3A%2F%2Ftracker.coppersurfer.tk%3A6969&amp;tr=udp%3A%2F%2Fexodus.desync.com%3A6969","seeders":0,"leechers":1,"uploader":"TvTeam","files":12,"time":1451991404,"description":"------------------------------------------------------------------------\r\n\r  https://www.torrenting.com\r\n\r\nSign up is OPEN - for time being. Come and have fun","torrent":{"xt":"urn:btih:f9197ce35a7830c5e981a5f373c9dc972b980972","amp;dn":"Degrassi.Next.Class.S01E01.XviD-AFG","amp;tr":["udp%3A%2F%2Ftracker.leechers-paradise.org%3A6969","udp%3A%2F%2Fzer0day.ch%3A1337","udp%3A%2F%2Fopen.demonii.com%3A1337","udp%3A%2F%2Ftracker.coppersurfer.tk%3A6969","udp%3A%2F%2Fexodus.desync.com%3A6969"],"infoHash":"f9197ce35a7830c5e981a5f373c9dc972b980972","infoHashBuffer":{"type":"Buffer","data":[249,25,124,227,90,120,48,197,233,129,165,243,115,201,220,151,43,152,9,114]},"announce":[],"urlList":[]}}