{"title":"My.Diet.Is.Better.Than.Yours.S01E01.720p.WEBRip.x264-WNN","uid":13349056,"size":1111337480,"categoryP":"video","categoryS":"hd___tv_shows","magnet":"?xt=urn:btih:fba9a7c08ac5bd26ef62206ffd36f804bbb1e1e1&amp;dn=My.Diet.Is.Better.Than.Yours.S01E01.720p.WEBRip.x264-WNN&amp;tr=udp%3A%2F%2Ftracker.leechers-paradise.org%3A6969&amp;tr=udp%3A%2F%2Fzer0day.ch%3A1337&amp;tr=udp%3A%2F%2Fopen.demonii.com%3A1337&amp;tr=udp%3A%2F%2Ftracker.coppersurfer.tk%3A6969&amp;tr=udp%3A%2F%2Fexodus.desync.com%3A6969","seeders":0,"leechers":0,"uploader":null,"files":3,"time":1454073989,"description":"2           2\r\n0     6     0\r\n1     h     1\r\n3     +     5\r\n\r\nRELEASE iNFO\r\n\r\nName...........: My.Diet.Is.Better.Than.Yours.S01E01.720p.WEBRip.x264-WNN\r\nSize...........: 1.04 GiB\r\nPacks..........: 23x50MB\r\nAired..........: 07/Jan/2016\r\nDuration.......: 42mn 13s\r\nVideo..........: h264, 1280x720 res, 30.000 fps, 3 360 Kbps\r\nAudio..........: AAC, 48.0 KHz / 24.0 KHz, 2ch, 127 Kbps\r\nSettings.......: Untouched\r\nEncodes........: 0\r\nClass..........: Stupid reality\r\nLink...........: http://thetvdb.com/?tab=series&amp;id=303474&amp;lid=7\r\n\r\nSHOW iNFO\r\n\r\nHosted by Shaun T, creator of the workout sensation &quot;Insanity,&quot; the new\r\nreality series &quot;My Diet Is Better Than Yours&quot; features celebrity\r\ntrainers coaching average Americans to lose weight and get in shape. Each\r\ntrainer brings his/her own individually designed and wildly diverse diet\r\nand exercise plan to their contestant, and works with them to change their\r\nlives and prove that &quot;My Diet Is Better Than Yours.&quot; In the end, one\r\nteam will reign victorious.\r\n\r\nRELEASE NOTES\r\n\r\nEnjoy!\r\n\r\nGROUP NOTES\r\n\r\nNo current needs.\r\n\r\nCONTACT iNFO","torrent":{"xt":"urn:btih:fba9a7c08ac5bd26ef62206ffd36f804bbb1e1e1","amp;dn":"My.Diet.Is.Better.Than.Yours.S01E01.720p.WEBRip.x264-WNN","amp;tr":["udp%3A%2F%2Ftracker.leechers-paradise.org%3A6969","udp%3A%2F%2Fzer0day.ch%3A1337","udp%3A%2F%2Fopen.demonii.com%3A1337","udp%3A%2F%2Ftracker.coppersurfer.tk%3A6969","udp%3A%2F%2Fexodus.desync.com%3A6969"],"infoHash":"fba9a7c08ac5bd26ef62206ffd36f804bbb1e1e1","infoHashBuffer":{"type":"Buffer","data":[251,169,167,192,138,197,189,38,239,98,32,111,253,54,248,4,187,177,225,225]},"announce":[],"urlList":[]}}